tests/__init__.py
tests/test_basic.py
thoughtful_agents/__init__.py
thoughtful_agents/models/__init__.py
thoughtful_agents/models/conversation.py
thoughtful_agents/models/enums.py
thoughtful_agents/models/memory.py
thoughtful_agents/models/mental_object.py
thoughtful_agents/models/participant.py
thoughtful_agents/models/thought.py
thoughtful_agents/utils/__init__.py
thoughtful_agents/utils/llm_api.py
thoughtful_agents/utils/saliency.py
thoughtful_agents/utils/text_splitter.py
thoughtful_agents/utils/thinking_engine.py
thoughtful_agents/utils/turn_taking_engine.py
thoughtful_agents-0.1.1.dist-info/LICENSE
thoughtful_agents-0.1.1.dist-info/METADATA
thoughtful_agents-0.1.1.dist-info/WHEEL
thoughtful_agents-0.1.1.dist-info/top_level.txt
thoughtful_agents-0.1.1.dist-info/RECORD
