Metadata-Version: 2.2
Name: thoughtful-agents
Version: 0.1.1
Summary: A framework for modeling agent thoughts and conversations
Home-page: https://github.com/xybruceliu/thoughtful-agents
Author: Xingyu Bruce Liu
Author-email: xingyuliu@ucla.edu
Project-URL: Documentation, https://github.com/xybruceliu/thoughtful-agents
Project-URL: Bug Reports, https://github.com/xybruceliu/thoughtful-agents/issues
Project-URL: Source Code, https://github.com/xybruceliu/thoughtful-agents
Keywords: ai agents,conversational ai,llm,proactive ai,inner thoughts,cognitive architecture,multi-agent,nlp,natural language processing,conversation
Classifier: Programming Language :: Python :: 3
Classifier: License :: OSI Approved :: Apache Software License
Classifier: Operating System :: OS Independent
Classifier: Development Status :: 4 - Beta
Classifier: Intended Audience :: Developers
Classifier: Intended Audience :: Science/Research
Classifier: Topic :: Scientific/Engineering :: Artificial Intelligence
Classifier: Topic :: Text Processing :: Linguistic
Requires-Python: >=3.8
License-File: LICENSE
Requires-Dist: numpy>=1.20.0
Requires-Dist: openai>=1.0.0
Requires-Dist: spacy>=3.0.0
Requires-Dist: typing-extensions>=4.0.0
Dynamic: author
Dynamic: author-email
Dynamic: classifier
Dynamic: description
Dynamic: description-content-type
Dynamic: home-page
Dynamic: keywords
Dynamic: project-url
Dynamic: requires-dist
Dynamic: requires-python
Dynamic: summary
